moss/__init__.py
moss/ems/__init__.py
moss/ems/emscatalog.py
moss/ems/emslayer.py
moss/ems/emsobjectclass.py
moss/ems/emsproject.py
moss/ems/emsqueryresult.py
moss/ems/emsservice.py
moss/ems/extra/__init__.py
moss/ems/extra/geometry_converter.py
moss/ems/extra/query_objectclass_layers.py
moss/ems/scripts/__init__.py
moss/ems/scripts/ems_cli_compare.py
moss/ems/scripts/ems_cli_dump.py
moss/ems/scripts/ems_cli_export.py
moss/ems/scripts/ems_cli_import.py
moss/ems/scripts/ems_cli_load.py
moss/ems/scripts/moss_emscli.py
moss/ems/scripts/utilities/__init__.py
moss/ems/scripts/utilities/promptutil.py
moss/ems/utilities/__init__.py
moss/ems/utilities/pagination_query.py
moss/ems/utilities/session_baseurl.py
moss/ems/utilities/sortutil.py
moss_emspy-2.5.1.data/scripts/moss_emscli.py
moss_emspy-2.5.1.dist-info/entry_points.txt
moss_emspy-2.5.1.dist-info/LICENSE
moss_emspy-2.5.1.dist-info/METADATA
moss_emspy-2.5.1.dist-info/WHEEL
moss_emspy-2.5.1.dist-info/RECORD
