Metadata-Version: 2.1
Name: moss_emspy
Version: 2.5.1
Summary: Package to interact with MOSS WEGA-EMS
Home-page: https://www.moss.de/
License: MIT
Keywords: wegaems
Author: M.O.S.S.Computer Grafik Systeme GmbH
Author-email: develop@moss.de
Maintainer: M.O.S.S.Computer Grafik Systeme GmbH
Maintainer-email: develop@moss.de
Requires-Python: >=3.7,<4
Classifier: Development Status :: 5 - Production/Stable
Classifier: Environment :: Console
Classifier: Environment :: Other Environment
Classifier: Intended Audience :: Developers
Classifier: License :: OSI Approved :: MIT License
Classifier: Operating System :: OS Independent
Classifier: Programming Language :: Python :: 3
Classifier: Programming Language :: Python :: 3.7
Classifier: Programming Language :: Python :: 3.8
Classifier: Programming Language :: Python :: 3.9
Classifier: Programming Language :: Python :: 3.10
Classifier: Programming Language :: Python :: 3.11
Classifier: Programming Language :: Python :: 3.12
Classifier: Programming Language :: Python :: 3.13
Classifier: Topic :: Software Development :: Libraries :: Python Modules
Requires-Dist: anytree (==2.8.0)
Requires-Dist: requests (>=2.27.0,<3.0.0)
Requires-Dist: tqdm (==4.64.0)
